pyzzy/__init__.py
pyzzy/compat.py
pyzzy/data/__init__.py
pyzzy/data/core.py
pyzzy/data/defaults.py
pyzzy/data/io_conf.py
pyzzy/data/io_json.py
pyzzy/data/io_raw.py
pyzzy/data/io_toml.py
pyzzy/data/io_yaml.py
pyzzy/logs/__init__.py
pyzzy/logs/core.py
pyzzy/logs/vars.py
pyzzy/utils/__init__.py
pyzzy/utils/dispatchers.py
pyzzy/utils/mappings.py
pyzzy/utils/nested.py
pyzzy/utils/templates.py
pyzzy-0.0.11.dist-info/LICENSE
pyzzy-0.0.11.dist-info/METADATA
pyzzy-0.0.11.dist-info/WHEEL
pyzzy-0.0.11.dist-info/top_level.txt
pyzzy-0.0.11.dist-info/RECORD
