Metadata-Version: 2.1
Name: pyzzy
Version: 0.0.11
Summary: Set of packages to simplify development in Python
Home-page: https://github.com/krakozaure/pyzzy
Author: krakozaure
Author-email: 
License: MIT License
Platform: UNKNOWN
Classifier: License :: OSI Approved :: MIT License
Classifier: Operating System :: OS Independent
Classifier: Programming Language :: Python :: 3
Classifier: Programming Language :: Python :: 3.4
Classifier: Programming Language :: Python :: 3.5
Classifier: Programming Language :: Python :: 3.6
Classifier: Programming Language :: Python :: 3.7
Classifier: Programming Language :: Python :: 3 :: Only
Classifier: Programming Language :: Python :: Implementation :: CPython
License-File: LICENSE
Requires-Dist: colorama
Requires-Dist: ruamel.yaml
Requires-Dist: toml
